pypandora/__init__.py
pypandora/api.py
pypandora/py.typed
pypandora-1.9.4.dist-info/LICENSE
pypandora-1.9.4.dist-info/METADATA
pypandora-1.9.4.dist-info/WHEEL
pypandora-1.9.4.dist-info/entry_points.txt
pypandora-1.9.4.dist-info/RECORD
