Metadata-Version: 2.3
Name: pypandora
Version: 1.9.4
Summary: Python CLI and module for pandora
License: BSD-3-Clause
Author: Raphaël Vinot
Author-email: raphael.vinot@circl.lu
Requires-Python: >=3.9
Classifier: Development Status :: 5 - Production/Stable
Classifier: Environment :: Console
Classifier: Intended Audience :: Information Technology
Classifier: Intended Audience :: Science/Research
Classifier: Intended Audience :: Telecommunications Industry
Classifier: License :: OSI Approved :: BSD License
Classifier: Operating System :: POSIX :: Linux
Classifier: Programming Language :: Python :: 3
Classifier: Programming Language :: Python :: 3.9
Classifier: Programming Language :: Python :: 3.10
Classifier: Programming Language :: Python :: 3.11
Classifier: Programming Language :: Python :: 3.12
Classifier: Programming Language :: Python :: 3.13
Classifier: Topic :: Internet
Classifier: Topic :: Security
Provides-Extra: docs
Requires-Dist: Sphinx (>=8.2.3) ; (python_version >= "3.11") and (extra == "docs")
Requires-Dist: requests (>=2.32.4)
Project-URL: Documentation, https://pypandora.readthedocs.io/en/latest/
Project-URL: Repository, https://github.com/pandora-analysis/pypandora
